JsonPreprocessor/CJsonPreprocessor.py
JsonPreprocessor/JsonPreprocessor.pdf
JsonPreprocessor/__init__.py
JsonPreprocessor/version.py
jsonpreprocessor-0.11.2.dist-info/licenses/LICENSE
jsonpreprocessor-0.11.2.dist-info/METADATA
jsonpreprocessor-0.11.2.dist-info/WHEEL
jsonpreprocessor-0.11.2.dist-info/top_level.txt
jsonpreprocessor-0.11.2.dist-info/RECORD
