Metadata-Version: 2.4
Name: JsonPreprocessor
Version: 0.11.2
Summary: Preprocessor for json files
Home-page: https://github.com/test-fullautomation/python-jsonpreprocessor
Author: Mai Dinh Nam Son
Author-email: son.maidinhnam@vn.bosch.com
Classifier: Programming Language :: Python :: 3
Classifier: License :: OSI Approved :: Apache Software License
Classifier: Operating System :: OS Independent
Classifier: Development Status :: 4 - Beta
Classifier: Intended Audience :: Developers
Classifier: Topic :: Software Development
Requires-Python: >=3.0
License-File: LICENSE
Requires-Dist: pydotdict
Dynamic: author
Dynamic: author-email
Dynamic: classifier
Dynamic: description
Dynamic: description-content-type
Dynamic: home-page
Dynamic: license-file
Dynamic: requires-dist
Dynamic: requires-python
Dynamic: summary
